fiduswriter/payment/__init__.py
fiduswriter/payment/admin.py
fiduswriter/payment/apps.py
fiduswriter/payment/models.py
fiduswriter/payment/signals.py
fiduswriter/payment/urls.py
fiduswriter/payment/validate.py
fiduswriter/payment/views.py
fiduswriter/payment/locale/bg/LC_MESSAGES/djangojs.mo
fiduswriter/payment/locale/bg/LC_MESSAGES/djangojs.po
fiduswriter/payment/locale/de/LC_MESSAGES/djangojs.mo
fiduswriter/payment/locale/de/LC_MESSAGES/djangojs.po
fiduswriter/payment/locale/es/LC_MESSAGES/djangojs.mo
fiduswriter/payment/locale/es/LC_MESSAGES/djangojs.po
fiduswriter/payment/locale/fr/LC_MESSAGES/djangojs.mo
fiduswriter/payment/locale/fr/LC_MESSAGES/djangojs.po
fiduswriter/payment/locale/it/LC_MESSAGES/djangojs.mo
fiduswriter/payment/locale/it/LC_MESSAGES/djangojs.po
fiduswriter/payment/locale/pt_BR/LC_MESSAGES/djangojs.mo
fiduswriter/payment/locale/pt_BR/LC_MESSAGES/djangojs.po
fiduswriter/payment/migrations/0001_initial.py
fiduswriter/payment/migrations/0002_auto_20191201_0241.py
fiduswriter/payment/migrations/0003_auto_20191201_0339.py
fiduswriter/payment/migrations/0004_auto_20201114_1140.py
fiduswriter/payment/migrations/__init__.py
fiduswriter/payment/static/css/payment.css
fiduswriter/payment/static/js/modules/payment/app.js
fiduswriter/payment/static/js/modules/payment/documents_overview.js
fiduswriter/payment/static/js/modules/payment/index.js
fiduswriter/payment/static/js/modules/payment/menu.js
fiduswriter/payment/static/js/modules/payment/page.js
fiduswriter/payment/static/js/modules/payment/prelogin.js
fiduswriter/payment/static/js/modules/payment/pricing.js
fiduswriter/payment/static/js/modules/payment/templates.js
fiduswriter/payment/static/js/plugins/app/payment.js
fiduswriter/payment/static/js/plugins/documents_overview/payment.js
fiduswriter/payment/static/js/plugins/menu/payment.js
fiduswriter/payment/static/js/plugins/prelogin/payment.js
fiduswriter_payment_paddle-4.0.0.dist-info/licenses/LICENSE
fiduswriter_payment_paddle-4.0.0.dist-info/METADATA
fiduswriter_payment_paddle-4.0.0.dist-info/WHEEL
fiduswriter_payment_paddle-4.0.0.dist-info/top_level.txt
fiduswriter_payment_paddle-4.0.0.dist-info/RECORD
