Metadata-Version: 2.4
Name: fiduswriter-payment-paddle
Version: 4.0.0
Summary: A Fidus Writer plugin to connect with Paddle.com as payment system
Home-page: https://www.github.com/fiduswriter/fiduswriter-payment-paddle
Author: Johannes Wilm
Author-email: Johannes Wilm <johannes@fiduswriter.org>
License: AGPL-3.0-or-later
Project-URL: repository, https://www.github.org/fiduswriter/fiduswriter-payment-paddle
Classifier: Environment :: Web Environment
Classifier: Framework :: Django
Classifier: Framework :: Django :: 5.1
Classifier: Intended Audience :: Developers
Classifier: License :: OSI Approved :: GNU Affero General Public License v3
Classifier: Operating System :: OS Independent
Classifier: Programming Language :: Python
Classifier: Programming Language :: Python :: 3
Classifier: Topic :: Internet :: WWW/HTTP
Classifier: Topic :: Internet :: WWW/HTTP :: Dynamic Content
License-File: LICENSE
Requires-Dist: pycryptodome==3.9.4
Requires-Dist: phpserialize==1.3
Dynamic: author
Dynamic: home-page
Dynamic: license-file
